HUD/agent_hud.py
HUD/demo_focus.py
HUD/file_tree.py
HUD/focus_tree.py
cli/__init__.py
cli/main.py
cli/tui.py
core/__init__.py
core/agent.py
core/agent_utils.py
core/code_edit.py
core/events.py
core/filesystem.py
core/history.py
core/llm_config.py
core/project.py
core/project_manager.py
core/signella.py
core/tool_utils.py
core/context_management/__init__.py
core/context_management/background_compaction.py
core/context_management/ground_truth.py
core/context_management/query.py
core/context_management/test_context_management.py
core/context_management/tokens.py
core/context_management/strategies/__init__.py
core/context_management/strategies/base.py
core/context_management/strategies/context_aware_gist.py
core/context_management/strategies/rolling_gist.py
core/context_management/strategies/test_strategies.py
core/legacy/context.py
core/legacy/turns.py
prism/README.md
prism/__init__.py
prism/adapter.py
prism/cleaner.py
prism/config.py
prism/graph.py
prism/models.py
prism/parsers.py
prism/remote_session.py
prism/scanner.py
prism/session.py
prism/snapshot.py
routes/__init__.py
routes/llm.py
routes/projects.py
routes/sessions.py
routes/shared.py
routes/socket_handlers.py
routes/ssh.py
static/favicon.png
static/css/highlight.css
static/workspace/css/base.css
static/workspace/css/index.css
static/workspace/css/layout.css
static/workspace/css/tabs.css
static/workspace/css/variables.css
static/workspace/css/components/chat.css
static/workspace/css/components/focus.css
static/workspace/css/components/preferences-base.css
static/workspace/css/components/preferences-browser.css
static/workspace/css/components/preferences-index.css
static/workspace/css/components/preferences-llm.css
static/workspace/css/components/preferences-projects-pane.css
static/workspace/css/components/preferences-projects.css
static/workspace/css/components/preferences-ssh.css
static/workspace/css/components/project-bar.css
static/workspace/css/components/settings.css
prismcode-0.1.13.dist-info/METADATA
prismcode-0.1.13.dist-info/WHEEL
prismcode-0.1.13.dist-info/entry_points.txt
prismcode-0.1.13.dist-info/RECORD
